MANIFEST.in
README-public.md
README.md
requirements-common.txt
requirements.txt
setup.cfg
setup.py
common/__init__.py
common/alchemy_instrumentation.py
common/consts.py
common/plan_collect_type.py
common/version.py
common/exporters/__init__.py
common/exporters/file_exporter.py
common/exporters/remote_exporter.py
common/instrumentations/__init__.py
common/instrumentations/consts.py
common/instrumentations/dummy.py
common/instrumentations/instrumentation_config.py
common/utils/__init__.py
common/utils/chunk.py
common/utils/env_var.py
common/utils/log.py
common/utils/once.py
common/utils/singleton_class.py
fastapialchemycollector/__init__.py
fastapialchemycollector/instruments.py
fastapialchemycollector.egg-info/PKG-INFO
fastapialchemycollector.egg-info/SOURCES.txt
fastapialchemycollector.egg-info/dependency_links.txt
fastapialchemycollector.egg-info/requires.txt
fastapialchemycollector.egg-info/top_level.txt