Metadata-Version: 2.1
Name: fastapialchemycollector
Version: 1.0.1
Summary: Metis log collector for FastAPI and SQLAlchemy
Home-page: https://github.com/metis-data/metis-python-collectors
Author: Metis dev
Author-email: devops@metisdata.io
License: UNKNOWN
Project-URL: Bug Tracker, https://github.com/metis-data/metis-python-collectors/issues
Platform: UNKNOWN
Requires-Python: >=3.6.*
